kittenai/__init__.py
kittenai/baiduai.py
kittenai-0.1.5.dist-info/LICENSE
kittenai-0.1.5.dist-info/METADATA
kittenai-0.1.5.dist-info/WHEEL
kittenai-0.1.5.dist-info/top_level.txt
kittenai-0.1.5.dist-info/RECORD
